setup.py
jyslee_distributions/Binomialdistribution.py
jyslee_distributions/Gaussiandistribution.py
jyslee_distributions/Generaldistribution.py
jyslee_distributions/__init__.py
jyslee_distributions.egg-info/PKG-INFO
jyslee_distributions.egg-info/SOURCES.txt
jyslee_distributions.egg-info/dependency_links.txt
jyslee_distributions.egg-info/not-zip-safe
jyslee_distributions.egg-info/top_level.txt